MANIFEST.in
README.rst
requirements.txt
setup.py
pyrs/__init__.py
pyrs/conf.py
pyrs.egg-info/PKG-INFO
pyrs.egg-info/SOURCES.txt
pyrs.egg-info/dependency_links.txt
pyrs.egg-info/not-zip-safe
pyrs.egg-info/pbr.json
pyrs.egg-info/top_level.txt
pyrs/env/__init__.py
pyrs/env/annotations.py
pyrs/env/configuration.py
pyrs/env/context.py
pyrs/env/tests/__init__.py
pyrs/env/tests/test_annotations.py
pyrs/env/tests/test_configuration.py
pyrs/env/tests/test_context.py